VirusLinux/__init__.py
VirusLinux-1.dist-info/DESCRIPTION.rst
VirusLinux-1.dist-info/METADATA
VirusLinux-1.dist-info/RECORD
VirusLinux-1.dist-info/WHEEL
VirusLinux-1.dist-info/metadata.json
VirusLinux-1.dist-info/top_level.txt
