Metadata-Version: 2.0
Name: VirusLinux
Version: 1
Summary: VirusLinux is made by kr rathod
Home-page: UNKNOWN
Author: Krrathod
Author-email: UNKNOWN
License: UNKNOWN
Platform: UNKNOWN
